{
  "headers": {
    "last-modified": "Fri, 25 Mar 2022 13:32:47 GMT",
    "accept-ranges": "bytes",
    "referrer-policy": "strict-origin-when-cross-origin",
    "age": "25346372",
    "x-amz-version-id": "EtZ1ohG4t3iztVlM3dn6Kz0gimFpILUt",
    "cross-origin-resource-policy": "same-origin",
    "etag": "\"839a4a3fbb8ec0b4332ec21006f527e4\"",
    "content-security-policy": "default-src 'none'; style-src 'unsafe-inline'; sandbox",
    "x-frame-options": "DENY",
    "cross-origin-embedder-policy": "same-origin",
    "content-type": "application/typescript; charset=utf-8",
    "cache-control": "public, max-age=31536000, immutable",
    "x-amz-cf-pop": "FRA56-P5",
    "via": "http/2 edgeproxy-h",
    "x-amz-replication-status": "COMPLETED",
    "access-control-allow-origin": "*",
    "content-length": "1528",
    "server-timing": "fetchSource;dur=6",
    "x-cache": "Hit from cloudfront",
    "x-content-type-options": "nosniff",
    "x-amz-cf-id": "I28whysUSdKD9ZFizD45MP3nx24yfNdZYzvjghq1v0yeQthL8G57aQ==",
    "date": "Thu, 23 Nov 2023 22:06:13 GMT",
    "cross-origin-opener-policy": "same-origin",
    "server": "deno/gcp-europe-west3",
    "vary": "Accept-Encoding, Origin",
    "strict-transport-security": "max-age=63072000; includeSubDomains; preload"
  },
  "url": "https://deno.land/std@0.132.0/async/deferred.ts",
  "now": {
    "secs_since_epoch": 1726123544,
    "nanos_since_epoch": 928997333
  }
}